circuits/04_stepper/src/lab3_stepper.v
`timescale 1ns/1ps
module lab3_stepper #(
parameter integer CLK_HZ = 50_000_000,
parameter integer STEP_HZ = 100
) (
input wire clk_50mhz,
input wire rst_p,
input wire enable,
input wire direction,
output reg [3:0] stepmotor
);
localparam integer STEP_CYCLES = CLK_HZ / STEP_HZ;
localparam integer COUNT_WIDTH = (STEP_CYCLES < 2) ? 1 : $clog2(STEP_CYCLES);
reg [COUNT_WIDTH-1:0] count;
reg [1:0] state;
(* ASYNC_REG = "TRUE" *) reg enable_meta, enable_sync;
(* ASYNC_REG = "TRUE" *) reg direction_meta, direction_sync;

always @(posedge clk_50mhz or posedge rst_p) begin
if (rst_p) begin
enable_meta <= 0; enable_sync <= 0;
direction_meta <= 0; direction_sync <= 0;
end else begin
enable_meta <= enable; enable_sync <= enable_meta;
direction_meta <= direction; direction_sync <= direction_meta;
end
end

always @(posedge clk_50mhz or posedge rst_p) begin
if (rst_p) begin
count <= 0;
state <= 0;
end else if (!enable_sync) begin
count <= 0;
end else if (count == STEP_CYCLES - 1) begin
count <= 0;
state <= direction_sync ? state - 1'b1 : state + 1'b1;
end else begin
count <= count + 1'b1;
end
end

always @* begin
case (state)
2'd0: stepmotor = 4'b0011;
2'd1: stepmotor = 4'b0110;
2'd2: stepmotor = 4'b1100;
default: stepmotor = 4'b1001;
endcase
end
endmodule

evidence/04_stepper/step1_modified/tb_stepper.sv
`timescale 1ns/1ps
module tb_stepper;
reg clk_50mhz=0,rst_p=1,enable=0,direction=0;
wire [3:0] stepmotor;
integer checks=0;
always #10 clk_50mhz=~clk_50mhz;
lab3_stepper #(.CLK_HZ(8),.STEP_HZ(1)) dut
(.clk_50mhz(clk_50mhz),.rst_p(rst_p),.enable(enable),.direction(direction),.stepmotor( stepmotor));
task check_value(input [3:0] value); begin #1;if(stepmotor!==value)$fatal(1,"got=%b expected=%b" ,stepmotor,value);checks++;
$display("CHECK number=%0d expected=%b observed=%b time=%0t",checks,value,stepmotor,$time);
end endtask
initial begin
$dumpfile("wave.vcd");$dumpvars(0,tb_stepper);
repeat(2)@(negedge clk_50mhz);rst_p=0;check_value(4'b0011);
enable=1;wait(dut.enable_sync);wait(dut.state==1);check_value(4'b0110);
wait(dut.state==2);check_value(4'b1100);
wait(dut.state==3);check_value(4'b1001);
wait(dut.state==0);check_value(4'b0011);
direction=1;wait(dut.direction_sync);wait(dut.state==3);check_value(4'b1001);
wait(dut.state==2);check_value(4'b1100);
enable=0;wait(!dut.enable_sync);repeat(12)@(posedge clk_50mhz);check_value(4'b1100);
$display("LAB3_STEPPER_PASS checks=%0d",checks); $finish;
end
initial begin #5000;$fatal(1,"timeout");end
endmodule

evidence/04_stepper/step1_modified/wave.vcd
$date
	Mon Sep 28 00:01:03 2026
$end
$version
	Icarus Verilog
$end
$timescale
	1ps
$end
$scope module tb_stepper $end
$var wire 4 ! stepmotor [3:0] $end
$var reg 1 " clk_50mhz $end
$var reg 1 # direction $end
$var reg 1 $ enable $end
$var reg 1 % rst_p $end
$var integer 32 & checks [31:0] $end
$scope module dut $end
$var wire 1 " clk_50mhz $end
$var wire 1 # direction $end
$var wire 1 $ enable $end
$var wire 1 % rst_p $end
$var parameter 32 ' CLK_HZ $end
$var parameter 32 ( COUNT_WIDTH $end
$var parameter 32 ) STEP_CYCLES $end
$var parameter 32 * STEP_HZ $end
$var reg 3 + count [2:0] $end
$var reg 1 , direction_meta $end
$var reg 1 - direction_sync $end
$var reg 1 . enable_meta $end
$var reg 1 / enable_sync $end
$var reg 2 0 state [1:0] $end
$var reg 4 1 stepmotor [3:0] $end
$upscope $end
$scope task check_value $end
$var reg 4 2 value [3:0] $end
$upscope $end
$upscope $end
$enddefinitions $end
$comment Show the parameter values. $end
$dumpall
b1 *
b1000 )
b11 (
b1000 '
$end
#0
$dumpvars
bx 2
bx 1
bx 0
x/
x.
x-
x,
bx +
b0 &
1%
0$
0#
0"
bx !
$end
#10000
b11 !
b11 1
0-
0,
0/
0.
b0 0
b0 +
1"
#20000
0"
#30000
1"
#40000
b11 2
0%
0"
#41000
1$
b1 &
#50000
1.
1"
#60000
0"
#70000
1/
1"
#80000
0"
#90000
b1 +
1"
#100000
0"
#110000
b10 +
1"
#120000
0"
#130000
b11 +
1"
#140000
0"
#150000
b100 +
1"
#160000
0"
#170000
b101 +
1"
#180000
0"
#190000
b110 +
1"
#200000
0"
#210000
b111 +
1"
#220000
0"
#230000
b110 !
b110 1
b110 2
b1 0
b0 +
1"
#231000
b10 &
#240000
0"
#250000
b1 +
1"
#260000
0"
#270000
b10 +
1"
#280000
0"
#290000
b11 +
1"
#300000
0"
#310000
b100 +
1"
#320000
0"
#330000
b101 +
1"
#340000
0"
#350000
b110 +
1"
#360000
0"
#370000
b111 +
1"
#380000
0"
#390000
b1100 !
b1100 1
b1100 2
b10 0
b0 +
1"
#391000
b11 &
#400000
0"
#410000
b1 +
1"
#420000
0"
#430000
b10 +
1"
#440000
0"
#450000
b11 +
1"
#460000
0"
#470000
b100 +
1"
#480000
0"
#490000
b101 +
1"
#500000
0"
#510000
b110 +
1"
#520000
0"
#530000
b111 +
1"
#540000
0"
#550000
b1001 !
b1001 1
b1001 2
b11 0
b0 +
1"
#551000
b100 &
#560000
0"
#570000
b1 +
1"
#580000
0"
#590000
b10 +
1"
#600000
0"
#610000
b11 +
1"
#620000
0"
#630000
b100 +
1"
#640000
0"
#650000
b101 +
1"
#660000
0"
#670000
b110 +
1"
#680000
0"
#690000
b111 +
1"
#700000
0"
#710000
b11 !
b11 1
b11 2
b0 0
b0 +
1"
#711000
1#
b101 &
#720000
0"
#730000
1,
b1 +
1"
#740000
0"
#750000
b10 +
1-
1"
#760000
0"
#770000
b11 +
1"
#780000
0"
#790000
b100 +
1"
#800000
0"
#810000
b101 +
1"
#820000
0"
#830000
b110 +
1"
#840000
0"
#850000
b111 +
1"
#860000
0"
#870000
b1001 !
b1001 1
b1001 2
b11 0
b0 +
1"
#871000
b110 &
#880000
0"
#890000
b1 +
1"
#900000
0"
#910000
b10 +
1"
#920000
0"
#930000
b11 +
1"
#940000
0"
#950000
b100 +
1"
#960000
0"
#970000
b101 +
1"
#980000
0"
#990000
b110 +
1"
#1000000
0"
#1010000
b111 +
1"
#1020000
0"
#1030000
b1100 !
b1100 1
b1100 2
b10 0
b0 +
1"
#1031000
0$
b111 &
#1040000
0"
#1050000
0.
b1 +
1"
#1060000
0"
#1070000
b10 +
0/
1"
#1080000
0"
#1090000
b0 +
1"
#1100000
0"
#1110000
1"
#1120000
0"
#1130000
1"
#1140000
0"
#1150000
1"
#1160000
0"
#1170000
1"
#1180000
0"
#1190000
1"
#1200000
0"
#1210000
1"
#1220000
0"
#1230000
1"
#1240000
0"
#1250000
1"
#1260000
0"
#1270000
1"
#1280000
0"
#1290000
1"
#1300000
0"
#1310000
1"
#1311000
b1000 &
