circuits/05_mmss_clock/src/sevenseg_decode.v
`timescale 1ns/1ps
module sevenseg_decode(
input wire [3:0] digit,
output reg [7:0] segments
);
always @* begin
case (digit)
4'd0: segments = 8'b1111_1100;
4'd1: segments = 8'b0110_0000;
4'd2: segments = 8'b1101_1010;
4'd3: segments = 8'b1111_0010;
4'd4: segments = 8'b0110_0110;
4'd5: segments = 8'b1011_0110;
4'd6: segments = 8'b1011_1110;
4'd7: segments = 8'b1110_0000;
4'd8: segments = 8'b1111_1110;
4'd9: segments = 8'b1111_0110;
default: segments = 8'b0000_0000;
endcase
end
endmodule

circuits/05_mmss_clock/src/mmss_counter.v
`timescale 1ns/1ps
module mmss_counter #(
parameter integer CLK_HZ = 50_000_000
) (
input wire clk,
input wire rst_p,
output reg [3:0] minute_tens,
output reg [3:0] minute_ones,
output reg [3:0] second_tens,
output reg [3:0] second_ones
);
localparam integer COUNT_WIDTH = (CLK_HZ < 2) ? 1 : $clog2(CLK_HZ);
reg [COUNT_WIDTH-1:0] subsecond;

always @(posedge clk or posedge rst_p) begin
if (rst_p) begin
subsecond <= 0;
minute_tens <= 0; minute_ones <= 0;
second_tens <= 0; second_ones <= 0;
end else if (subsecond == CLK_HZ - 1) begin
subsecond <= 0;
if (second_ones != 9)
second_ones <= second_ones + 1'b1;
else begin
second_ones <= 0;
if (second_tens != 5)
second_tens <= second_tens + 1'b1;
else begin
second_tens <= 0;
if (minute_ones != 9)
minute_ones <= minute_ones + 1'b1;
else begin
minute_ones <= 0;
if (minute_tens != 5)
minute_tens <= minute_tens + 1'b1;
else
minute_tens <= 0;
end
end
end
end else begin
subsecond <= subsecond + 1'b1;
end
end
endmodule

evidence/05_mmss_clock/clk4_modified/tb_mmss_counter.sv
`timescale 1ns/1ps
module tb_mmss_counter;
reg clk_50mhz=0,rst_p=1;
wire [3:0] mt,mo,st,so;
reg [3:0] decode_digit;
wire [7:0] decoded_segments;
integer checks=0;
always #10 clk_50mhz=~clk_50mhz;
mmss_counter #(.CLK_HZ(4)) dut(.clk(clk_50mhz),.rst_p(rst_p),.minute_tens(mt),.minute_ones(mo) ,.second_tens(st),.second_ones(so));
sevenseg_decode decoder(.digit(decode_digit),.segments(decoded_segments));
task advance(input integer seconds);begin repeat (seconds*2)@(posedge clk_50mhz);#1;end endtask
task check_time(input integer emt,input integer emo,input integer est,input integer eso);
begin if (mt!==emt||mo!==emo||st!==est||so!==eso)$fatal(1,"time=%0d%0d:%0d%0d",mt,mo,st,so); checks++;
$display("CHECK number=%0d clock=%0d%0d:%0d%0d time=%0t",checks,mt,mo,st,so,$time);
end endtask
initial begin
$dumpfile("wave.vcd");$dumpvars(0,tb_mmss_counter);
decode_digit=0;#1;if(decoded_segments!==8'b1111_1100)$fatal(1,"digit 0 decode");checks++;
decode_digit=9;#1;if(decoded_segments!==8'b1111_0110)$fatal(1,"digit 9 decode");checks++;
repeat(2)@(negedge clk_50mhz);rst_p=0;check_time(0,0,0,0);
advance(10);check_time(0,0,1,0);
advance(50);check_time(0,1,0,0);
advance(3539);check_time(5,9,5,9);
advance(1);check_time(0,0,0,0);
$display("LAB3_MMSS_PASS checks=%0d",checks); $finish;
end
initial begin #200000;$fatal(1,"timeout");end
endmodule

evidence/05_mmss_clock/clk4_modified/wave.vcd
$date
	Mon Sep 28 00:16:23 2026
$end
$version
	Icarus Verilog
$end
$timescale
	1ps
$end
$scope module tb_mmss_counter $end
$var wire 4 ! st [3:0] $end
$var wire 4 " so [3:0] $end
$var wire 4 # mt [3:0] $end
$var wire 4 $ mo [3:0] $end
$var wire 8 % decoded_segments [7:0] $end
$var reg 1 & clk_50mhz $end
$var reg 4 ' decode_digit [3:0] $end
$var reg 1 ( rst_p $end
$var integer 32 ) checks [31:0] $end
$scope module decoder $end
$var wire 4 * digit [3:0] $end
$var reg 8 + segments [7:0] $end
$upscope $end
$scope module dut $end
$var wire 1 & clk $end
$var wire 1 ( rst_p $end
$var parameter 32 , CLK_HZ $end
$var parameter 32 - COUNT_WIDTH $end
$var reg 4 . minute_ones [3:0] $end
$var reg 4 / minute_tens [3:0] $end
$var reg 4 0 second_ones [3:0] $end
$var reg 4 1 second_tens [3:0] $end
$var reg 2 2 subsecond [1:0] $end
$upscope $end
$scope task advance $end
$var integer 32 3 seconds [31:0] $end
$upscope $end
$scope task check_time $end
$var integer 32 4 emo [31:0] $end
$var integer 32 5 emt [31:0] $end
$var integer 32 6 eso [31:0] $end
$var integer 32 7 est [31:0] $end
$upscope $end
$upscope $end
$enddefinitions $end
$comment Show the parameter values. $end
$dumpall
b10 -
b100 ,
$end
#0
$dumpvars
bx 7
bx 6
bx 5
bx 4
bx 3
bx 2
bx 1
bx 0
bx /
bx .
b11111100 +
b0 *
b0 )
1(
b0 '
0&
b11111100 %
bx $
bx #
bx "
bx !
$end
#1000
b11110110 %
b11110110 +
b1001 '
b1001 *
b1 )
#2000
b10 )
#10000
b0 "
b0 0
b0 !
b0 1
b0 $
b0 .
b0 #
b0 /
b0 2
1&
#20000
0&
#30000
1&
#40000
b1010 3
b11 )
b0 6
b0 7
b0 4
b0 5
0(
0&
#50000
b1 2
1&
#60000
0&
#70000
b10 2
1&
#80000
0&
#90000
b11 2
1&
#100000
0&
#110000
b1 "
b1 0
b0 2
1&
#120000
0&
#130000
b1 2
1&
#140000
0&
#150000
b10 2
1&
#160000
0&
#170000
b11 2
1&
#180000
0&
#190000
b10 "
b10 0
b0 2
1&
#200000
0&
#210000
b1 2
1&
#220000
0&
#230000
b10 2
1&
#240000
0&
#250000
b11 2
1&
#260000
0&
#270000
b11 "
b11 0
b0 2
1&
#280000
0&
#290000
b1 2
1&
#300000
0&
#310000
b10 2
1&
#320000
0&
#330000
b11 2
1&
#340000
0&
#350000
b100 "
b100 0
b0 2
1&
#360000
0&
#370000
b1 2
1&
#380000
0&
#390000
b10 2
1&
#400000
0&
#410000
b11 2
1&
#420000
0&
#430000
b101 "
b101 0
b0 2
1&
#431000
b1 7
