circuits/03_piezo/src/lab3_piezo.v
`timescale 1ns/1ps
module lab3_piezo #(
parameter integer CLK_HZ = 50_000_000,
parameter integer TONE_HZ = 294
) (
input wire clk_50mhz,
input wire rst_p,
output reg piezo
);
localparam integer HALF_PERIOD = CLK_HZ / (2 * TONE_HZ);
localparam integer COUNT_WIDTH = (HALF_PERIOD < 2) ? 1 : $clog2(HALF_PERIOD);
reg [COUNT_WIDTH-1:0] count;

always @(posedge clk_50mhz or posedge rst_p) begin
if (rst_p) begin
count <= 0;
piezo <= 0;
end else if (count == HALF_PERIOD - 1) begin
count <= 0;
piezo <= ~piezo;
end else begin
count <= count + 1'b1;
end
end
endmodule

evidence/03_piezo/tone50_modified/tb_piezo.sv
`timescale 1ns/1ps
module tb_piezo;
reg clk_50mhz=0,rst_p=1;
wire piezo;
reg previous_piezo=0;
integer cycles,last_cycle=-1,edges=0;
always #10 clk_50mhz=~clk_50mhz;
lab3_piezo #(.CLK_HZ(1000),.TONE_HZ(50)) dut(.clk_50mhz(clk_50mhz),.rst_p(rst_p),.piezo(piezo) );
initial begin
$dumpfile("wave.vcd");$dumpvars(0,tb_piezo);
repeat(3)@(negedge clk_50mhz);rst_p=0;
for(cycles=1;cycles<=25;cycles=cycles+1)begin
@(posedge clk_50mhz);#1;
if(piezo !== ((cycles / 5) % 2 == 1))
    $fatal(1,"cycle=%0d expected=%0d piezo=%b",cycles,(cycles / 5) % 2,piezo);
if(piezo !== previous_piezo)begin
if(last_cycle>=0 && cycles-last_cycle!=5)$fatal(1,"half period=%0d",cycles-last_cycle);
last_cycle=cycles;edges=edges+1;
$display("EDGE cycle=%0d piezo=%b time=%0t",cycles,piezo,$time);
end
previous_piezo=piezo;
end
if(edges!=5)$fatal(1,"too few edges");
$display("LAB3_PIEZO_PASS edges=%0d",edges); $finish;
end
initial begin #5000;$fatal(1,"timeout");end
endmodule

evidence/03_piezo/icarus_baseline/wave.vcd
$date
	Sun Sep 27 23:34:13 2026
$end
$version
	Icarus Verilog
$end
$timescale
	1ps
$end
$scope module tb_piezo $end
$var wire 1 ! piezo $end
$var reg 1 " clk_50mhz $end
$var reg 1 # previous_piezo $end
$var reg 1 $ rst_p $end
$var integer 32 % cycles [31:0] $end
$var integer 32 & edges [31:0] $end
$var integer 32 ' last_cycle [31:0] $end
$scope module dut $end
$var wire 1 " clk_50mhz $end
$var wire 1 $ rst_p $end
$var parameter 32 ( CLK_HZ $end
$var parameter 32 ) COUNT_WIDTH $end
$var parameter 32 * HALF_PERIOD $end
$var parameter 32 + TONE_HZ $end
$var reg 3 , count [2:0] $end
$var reg 1 ! piezo $end
$upscope $end
$upscope $end
$enddefinitions $end
$comment Show the parameter values. $end
$dumpall
b1100100 +
b101 *
b11 )
b1111101000 (
$end
#0
$dumpvars
bx ,
b11111111111111111111111111111111 '
b0 &
bx %
1$
0#
0"
x!
$end
#10000
0!
b0 ,
1"
#20000
0"
#30000
1"
#40000
0"
#50000
1"
#60000
b1 %
0$
0"
#70000
b1 ,
1"
#71000
b10 %
#80000
0"
#90000
b10 ,
1"
#91000
b11 %
#100000
0"
#110000
b11 ,
1"
#111000
b100 %
#120000
0"
#130000
b100 ,
1"
#131000
b101 %
#140000
0"
#150000
1!
b0 ,
1"
#151000
b110 %
1#
b1 &
b101 '
#160000
0"
#170000
b1 ,
1"
#171000
b111 %
#180000
0"
#190000
b10 ,
1"
#191000
b1000 %
#200000
0"
#210000
b11 ,
1"
#211000
b1001 %
#220000
0"
#230000
b100 ,
1"
#231000
b1010 %
#240000
0"
#250000
0!
b0 ,
1"
#251000
b1011 %
0#
b10 &
b1010 '
#260000
0"
#270000
b1 ,
1"
#271000
b1100 %
#280000
0"
#290000
b10 ,
1"
#291000
b1101 %
#300000
0"
#310000
b11 ,
1"
#311000
b1110 %
#320000
0"
#330000
b100 ,
1"
#331000
b1111 %
#340000
0"
#350000
1!
b0 ,
1"
#351000
b10000 %
1#
b11 &
b1111 '
#360000
0"
#370000
b1 ,
1"
#371000
b10001 %
#380000
0"
#390000
b10 ,
1"
#391000
b10010 %
#400000
0"
#410000
b11 ,
1"
#411000
b10011 %
#420000
0"
#430000
b100 ,
1"
#431000
b10100 %
#440000
0"
#450000
0!
b0 ,
1"
#451000
b10101 %
0#
b100 &
b10100 '
#460000
0"
#470000
b1 ,
1"
#471000
b10110 %
#480000
0"
#490000
b10 ,
1"
#491000
b10111 %
#500000
0"
#510000
b11 ,
1"
#511000
b11000 %
#520000
0"
#530000
b100 ,
1"
#531000
b11001 %
#540000
0"
#550000
1!
b0 ,
1"
#551000
b11010 %
1#
b101 &
b11001 '
