circuits/02_rgb_pwm/src/pwm_channel.v
`timescale 1ns/1ps
module pwm_channel #(
parameter integer PERIOD_CYCLES = 50_000,
parameter integer LEVELS = 10
) (
input wire clk,
input wire rst_p,
input wire [3:0] level,
output reg pwm
);
localparam integer COUNT_WIDTH = (PERIOD_CYCLES < 2) ? 1 : $clog2(PERIOD_CYCLES);
reg [COUNT_WIDTH-1:0] count;
integer threshold;

always @* begin
if (level >= LEVELS)
threshold = PERIOD_CYCLES;
else
threshold = (PERIOD_CYCLES * level) / LEVELS;
end

always @(posedge clk or posedge rst_p) begin
if (rst_p) begin
count <= {COUNT_WIDTH{1'b0}};
pwm <= 1'b0;
end else begin
pwm <= (count < threshold);
if (count == PERIOD_CYCLES - 1)
count <= {COUNT_WIDTH{1'b0}};
else
count <= count + 1'b1;
end
end
endmodule

circuits/01_led_pwm/src/button_onepulse.v
`timescale 1ns/1ps
module button_onepulse #(
parameter integer STABLE_CYCLES = 1_000_000
) (
input wire clk,
input wire rst_p,
input wire button,
output reg pulse
);
(* ASYNC_REG = "TRUE" *) reg button_meta;
(* ASYNC_REG = "TRUE" *) reg button_sync;
localparam integer COUNT_WIDTH = (STABLE_CYCLES < 2) ? 1 : $clog2(STABLE_CYCLES);
reg [COUNT_WIDTH-1:0] stable_count;
reg accepted;

always @(posedge clk or posedge rst_p) begin
if (rst_p) begin
button_meta <= 1'b0;
button_sync <= 1'b0;
end else begin
button_meta <= button;
button_sync <= button_meta;
end
end

always @(posedge clk or posedge rst_p) begin
if (rst_p) begin
stable_count <= {COUNT_WIDTH{1'b0}};
accepted <= 1'b0;
pulse <= 1'b0;
end else begin
pulse <= 1'b0;
if (button_sync == accepted) begin
stable_count <= {COUNT_WIDTH{1'b0}};
end else if (stable_count == STABLE_CYCLES - 1) begin
stable_count <= {COUNT_WIDTH{1'b0}};
accepted <= button_sync;
pulse <= button_sync;
end else begin
stable_count <= stable_count + 1'b1;
end
end
end
endmodule

evidence/02_rgb_pwm/red_initial1_modified/lab3_rgb_pwm.v
`timescale 1ns/1ps
module lab3_rgb_pwm #(
parameter integer CLK_HZ = 50_000_000,
parameter integer PWM_HZ = 1_000,
parameter integer LEVELS = 10,
parameter integer DEBOUNCE_CYCLES = 1_000_000
) (
input wire clk_50mhz,
input wire rst_p,
input wire button_r,
input wire button_g,
input wire button_b,
output wire [3:0] led_r,
output wire [3:0] led_g,
output wire [3:0] led_b
);
wire press_r, press_g, press_b;
wire pwm_r, pwm_g, pwm_b;
reg [3:0] level_r, level_g, level_b;

button_onepulse #(.STABLE_CYCLES(DEBOUNCE_CYCLES)) u_button_r (
.clk(clk_50mhz), .rst_p(rst_p), .button(button_r), .pulse(press_r));
button_onepulse #(.STABLE_CYCLES(DEBOUNCE_CYCLES)) u_button_g (
.clk(clk_50mhz), .rst_p(rst_p), .button(button_g), .pulse(press_g));
button_onepulse #(.STABLE_CYCLES(DEBOUNCE_CYCLES)) u_button_b (
.clk(clk_50mhz), .rst_p(rst_p), .button(button_b), .pulse(press_b));

always @(posedge clk_50mhz or posedge rst_p) begin
if (rst_p) begin
level_r <= 1; level_g <= 0; level_b <= 0;
end else begin
if (press_r) level_r <= (level_r == LEVELS) ? 0 : level_r + 1'b1;
if (press_g) level_g <= (level_g == LEVELS) ? 0 : level_g + 1'b1;
if (press_b) level_b <= (level_b == LEVELS) ? 0 : level_b + 1'b1;
end
end

pwm_channel #(.PERIOD_CYCLES(CLK_HZ / PWM_HZ), .LEVELS(LEVELS)) u_pwm_r
(.clk(clk_50mhz), .rst_p(rst_p), .level(level_r), .pwm(pwm_r));
pwm_channel #(.PERIOD_CYCLES(CLK_HZ / PWM_HZ), .LEVELS(LEVELS)) u_pwm_g
(.clk(clk_50mhz), .rst_p(rst_p), .level(level_g), .pwm(pwm_g));
pwm_channel #(.PERIOD_CYCLES(CLK_HZ / PWM_HZ), .LEVELS(LEVELS)) u_pwm_b
(.clk(clk_50mhz), .rst_p(rst_p), .level(level_b), .pwm(pwm_b));

assign led_r = {4{pwm_r}};
assign led_g = {4{pwm_g}};
assign led_b = {4{pwm_b}};
endmodule

evidence/02_rgb_pwm/red_initial0_restored/tb_rgb_pwm.sv
`timescale 1ns/1ps
module tb_rgb_pwm;
reg clk_50mhz=0,rst_p=1,button_r=0,button_g=0,button_b=0;
wire [3:0] led_r,led_g,led_b;
integer checks=0,i,hr,hg,hb;
always #10 clk_50mhz=~clk_50mhz;
lab3_rgb_pwm #(.CLK_HZ(1000),.PWM_HZ(100),.LEVELS(10),.DEBOUNCE_CYCLES(2)) dut
(.clk_50mhz(clk_50mhz),.rst_p(rst_p),.button_r(button_r),.button_g(button_g),.button_b( button_b),
.led_r(led_r),.led_g(led_g),.led_b(led_b));

task press_r; begin @(negedge clk_50mhz); button_r=1;repeat(6)@(negedge clk_50mhz);button_r=0;repeat(6)@(negedge clk_50mhz);end endtask
task press_g; begin @(negedge clk_50mhz); button_g=1;repeat(6)@(negedge clk_50mhz);button_g=0;repeat(6)@(negedge clk_50mhz);end endtask
task press_b; begin @(negedge clk_50mhz); button_b=1;repeat(6)@(negedge clk_50mhz);button_b=0;repeat(6)@(negedge clk_50mhz);end endtask
task measure(input integer er,input integer eg,input integer eb);
begin
wait(dut.u_pwm_r.count==0);hr=0;hg=0;hb=0;
for(i=0;i<10;i=i+1)begin @(posedge clk_50mhz);#1;hr+=led_r[0];hg+=led_g[0];hb+=led_b[0];end
if(hr!==er||hg!==eg||hb!==eb)$fatal(1,"rgb high=%0d,%0d,%0d",hr,hg,hb);
$display("CHECK expected=%0d,%0d,%0d observed=%0d,%0d,%0d time=%0t",er,eg,eb,hr,hg,hb,$time);
checks=checks+1;
end endtask
initial begin
$dumpfile("wave.vcd");$dumpvars(0,tb_rgb_pwm);
repeat(3)@(negedge clk_50mhz);rst_p=0;
repeat(2)press_r();repeat(5)press_g();repeat(8)press_b();measure(2,5,8);
press_r();measure(3,5,8);
$display("LAB3_RGB_PWM_PASS checks=%0d",checks); $finish;
end
initial begin #30000;$fatal(1,"timeout");end
endmodule

evidence/02_rgb_pwm/red_initial1_modified/wave.vcd
$date
	Sun Sep 27 23:31:05 2026
$end
$version
	Icarus Verilog
$end
$timescale
	1ps
$end
$scope module tb_rgb_pwm $end
$var wire 4 ! led_r [3:0] $end
$var wire 4 " led_g [3:0] $end
$var wire 4 # led_b [3:0] $end
$var reg 1 $ button_b $end
$var reg 1 % button_g $end
$var reg 1 & button_r $end
$var reg 1 ' clk_50mhz $end
$var reg 1 ( rst_p $end
$var integer 32 ) checks [31:0] $end
$var integer 32 * hb [31:0] $end
$var integer 32 + hg [31:0] $end
$var integer 32 , hr [31:0] $end
$var integer 32 - i [31:0] $end
$scope module dut $end
$var wire 1 $ button_b $end
$var wire 1 % button_g $end
$var wire 1 & button_r $end
$var wire 1 ' clk_50mhz $end
$var wire 1 ( rst_p $end
$var wire 1 . pwm_r $end
$var wire 1 / pwm_g $end
$var wire 1 0 pwm_b $end
$var wire 1 1 press_r $end
$var wire 1 2 press_g $end
$var wire 1 3 press_b $end
$var wire 4 4 led_r [3:0] $end
$var wire 4 5 led_g [3:0] $end
$var wire 4 6 led_b [3:0] $end
$var parameter 32 7 CLK_HZ $end
$var parameter 32 8 DEBOUNCE_CYCLES $end
$var parameter 32 9 LEVELS $end
$var parameter 32 : PWM_HZ $end
$var reg 4 ; level_b [3:0] $end
$var reg 4 < level_g [3:0] $end
$var reg 4 = level_r [3:0] $end
$scope module u_button_b $end
$var wire 1 $ button $end
$var wire 1 ' clk $end
$var wire 1 ( rst_p $end
$var parameter 32 > COUNT_WIDTH $end
$var parameter 32 ? STABLE_CYCLES $end
$var reg 1 @ accepted $end
$var reg 1 A button_meta $end
$var reg 1 B button_sync $end
$var reg 1 3 pulse $end
$var reg 1 C stable_count $end
$upscope $end
$scope module u_button_g $end
$var wire 1 % button $end
$var wire 1 ' clk $end
$var wire 1 ( rst_p $end
$var parameter 32 D COUNT_WIDTH $end
$var parameter 32 E STABLE_CYCLES $end
$var reg 1 F accepted $end
$var reg 1 G button_meta $end
$var reg 1 H button_sync $end
$var reg 1 2 pulse $end
$var reg 1 I stable_count $end
$upscope $end
$scope module u_button_r $end
$var wire 1 & button $end
$var wire 1 ' clk $end
$var wire 1 ( rst_p $end
$var parameter 32 J COUNT_WIDTH $end
$var parameter 32 K STABLE_CYCLES $end
$var reg 1 L accepted $end
$var reg 1 M button_meta $end
$var reg 1 N button_sync $end
$var reg 1 1 pulse $end
$var reg 1 O stable_count $end
$upscope $end
$scope module u_pwm_b $end
$var wire 1 ' clk $end
$var wire 4 P level [3:0] $end
$var wire 1 ( rst_p $end
$var parameter 32 Q COUNT_WIDTH $end
$var parameter 32 R LEVELS $end
$var parameter 32 S PERIOD_CYCLES $end
$var reg 4 T count [3:0] $end
$var reg 1 0 pwm $end
$var integer 32 U threshold [31:0] $end
$upscope $end
$scope module u_pwm_g $end
$var wire 1 ' clk $end
$var wire 4 V level [3:0] $end
$var wire 1 ( rst_p $end
$var parameter 32 W COUNT_WIDTH $end
$var parameter 32 X LEVELS $end
$var parameter 32 Y PERIOD_CYCLES $end
$var reg 4 Z count [3:0] $end
$var reg 1 / pwm $end
$var integer 32 [ threshold [31:0] $end
$upscope $end
$scope module u_pwm_r $end
$var wire 1 ' clk $end
$var wire 4 \ level [3:0] $end
$var wire 1 ( rst_p $end
$var parameter 32 ] COUNT_WIDTH $end
$var parameter 32 ^ LEVELS $end
$var parameter 32 _ PERIOD_CYCLES $end
$var reg 4 ` count [3:0] $end
$var reg 1 . pwm $end
$var integer 32 a threshold [31:0] $end
$upscope $end
$upscope $end
$scope task measure $end
$var integer 32 b eb [31:0] $end
$var integer 32 c eg [31:0] $end
$var integer 32 d er [31:0] $end
$upscope $end
$scope task press_b $end
$upscope $end
$scope task press_g $end
$upscope $end
$scope task press_r $end
$upscope $end
$upscope $end
$enddefinitions $end
$comment Show the parameter values. $end
$dumpall
b1010 _
b1010 ^
b100 ]
b1010 Y
b1010 X
b100 W
b1010 S
b1010 R
b100 Q
b10 K
b1 J
b10 E
b1 D
b10 ?
b1 >
b1100100 :
b1010 9
b10 8
b1111101000 7
$end
#0
$dumpvars
bx d
bx c
bx b
bx a
bx `
bx \
bx [
bx Z
bx V
bx U
bx T
bx P
xO
xN
xM
xL
xI
xH
xG
xF
xC
xB
xA
x@
bx =
bx <
bx ;
bx 6
bx 5
bx 4
x3
x2
x1
x0
x/
x.
bx -
bx ,
bx +
bx *
b0 )
1(
0'
0&
0%
0$
bx #
bx "
bx !
$end
#10000
b0 U
b0 [
b1 a
0N
0M
01
0L
0O
0H
0G
02
0F
0I
0B
0A
03
0@
0C
b0 !
b0 4
0.
b0 `
b0 "
b0 5
0/
b0 Z
b0 #
b0 6
00
b0 T
b0 ;
b0 P
b0 <
b0 V
b1 =
b1 \
1'
#20000
0'
#30000
1'
#40000
0'
#50000
1'
#60000
0(
0'
#70000
b1 T
b1 Z
b1 `
b1111 !
b1111 4
1.
1'
#80000
1&
0'
#90000
1M
b10 `
b0 !
b0 4
0.
b10 Z
b10 T
1'
#100000
0'
#110000
b11 T
b11 Z
b11 `
1N
1'
#120000
0'
#130000
1O
b100 `
b100 Z
b100 T
1'
#140000
0'
#150000
b101 T
b101 Z
b101 `
11
1L
0O
1'
#160000
0'
#170000
b10 a
01
b110 `
b110 Z
b110 T
b10 =
b10 \
1'
#180000
0'
#190000
b111 T
b111 Z
b111 `
1'
#200000
0&
0'
#210000
0M
b1000 `
b1000 Z
b1000 T
1'
#220000
0'
#230000
b1001 T
b1001 Z
b1001 `
0N
1'
#240000
0'
#250000
1O
b0 `
b0 Z
b0 T
1'
#260000
0'
#270000
b1 T
b1 Z
b1 `
b1111 !
b1111 4
1.
0L
0O
1'
#280000
0'
#290000
b10 `
b10 Z
b10 T
1'
#300000
0'
#310000
b11 T
b11 Z
b11 `
b0 !
b0 4
0.
1'
#320000
0'
#330000
b100 `
b100 Z
b100 T
1'
#340000
1&
0'
#350000
b101 T
b101 Z
b101 `
1M
1'
#360000
0'
#370000
1N
b110 `
b110 Z
b110 T
1'
#380000
0'
#390000
b111 T
b111 Z
b111 `
1O
1'
#400000
0'
#410000
11
1L
0O
b1000 `
b1000 Z
b1000 T
1'
#420000
0'
#430000
b11 a
b11 =
b11 \
b1001 T
b1001 Z
b1001 `
01
1'
#440000
0'
#450000
b0 `
b0 Z
b0 T
1'
#460000
0&
0'
#470000
b1 T
b1 Z
b1 `
b1111 !
b1111 4
1.
0M
1'
#480000
0'
#490000
0N
b10 `
b10 Z
b10 T
1'
#500000
0'
#510000
b11 T
b11 Z
b11 `
1O
1'
#520000
0'
#530000
0L
0O
b100 `
b0 !
b0 4
0.
b100 Z
b100 T
1'
#540000
0'
#550000
b101 T
b101 Z
b101 `
1'
#560000
0'
#570000
b110 `
b110 Z
b110 T
1'
#580000
0'
#590000
b111 T
b111 Z
b111 `
1'
#600000
1%
0'
#610000
1G
b1000 `
b1000 Z
b1000 T
1'
#620000
0'
#630000
b1001 T
b1001 Z
b1001 `
1H
1'
#640000
0'
#650000
1I
b0 `
b0 Z
b0 T
1'
#660000
0'
#670000
b1 T
b1 Z
b1 `
b1111 !
b1111 4
1.
12
1F
0I
1'
#680000
0'
#690000
b1 [
02
b10 `
b10 Z
b10 T
b1 <
b1 V
1'
#700000
0'
#710000
b11 T
b11 Z
b11 `
1'
#720000
0%
0'
#730000
0G
b100 `
b0 !
b0 4
0.
b100 Z
b100 T
1'
#740000
0'
#750000
b101 T
b101 Z
b101 `
0H
1'
#760000
0'
#770000
1I
b110 `
b110 Z
b110 T
1'
#780000
0'
#790000
b111 T
b111 Z
b111 `
0F
0I
1'
#800000
0'
#810000
b1000 `
b1000 Z
b1000 T
1'
#820000
0'
#830000
b1001 T
b1001 Z
b1001 `
1'
#840000
0'
#850000
b0 `
b0 Z
b0 T
1'
#860000
1%
0'
#870000
b1 T
b1 Z
b1111 "
b1111 5
1/
b1 `
b1111 !
b1111 4
1.
1G
1'
#880000
0'
#890000
1H
b10 `
b10 Z
b0 "
b0 5
0/
b10 T
1'
#900000
0'
#910000
b11 T
b11 Z
b11 `
1I
1'
#920000
0'
#930000
12
1F
0I
b100 `
b0 !
b0 4
0.
b100 Z
b100 T
1'
#940000
0'
#950000
b10 [
b10 <
b10 V
b101 T
b101 Z
b101 `
02
1'
#960000
0'
#970000
b110 `
b110 Z
b110 T
1'
#980000
0%
0'
#990000
b111 T
b111 Z
b111 `
0G
1'
#1000000
0'
#1010000
0H
b1000 `
b1000 Z
b1000 T
1'
#1020000
0'
#1030000
b1001 T
b1001 Z
b1001 `
1I
1'
#1040000
0'
#1050000
0F
0I
b0 `
b0 Z
b0 T
1'
#1060000
0'
#1070000
b1 T
b1 Z
b1111 "
b1111 5
1/
b1 `
b1111 !
b1111 4
1.
1'
#1080000
0'
#1090000
b10 `
b10 Z
b10 T
1'
#1100000
0'
#1110000
b11 T
b11 Z
b0 "
b0 5
0/
b11 `
1'
#1120000
1%
0'
#1130000
1G
b100 `
b0 !
b0 4
0.
b100 Z
b100 T
1'
#1140000
0'
#1150000
b101 T
b101 Z
b101 `
1H
1'
#1160000
0'
#1170000
1I
b110 `
b110 Z
b110 T
1'
#1180000
0'
#1190000
b111 T
b111 Z
b111 `
12
1F
0I
1'
#1200000
0'
#1210000
b11 [
02
b1000 `
b1000 Z
b1000 T
b11 <
b11 V
1'
#1220000
0'
#1230000
b1001 T
b1001 Z
b1001 `
1'
#1240000
0%
0'
#1250000
0G
b0 `
b0 Z
b0 T
1'
#1260000
0'
#1270000
b1 T
b1 Z
b1111 "
b1111 5
1/
b1 `
b1111 !
b1111 4
1.
0H
1'
#1280000
0'
#1290000
1I
b10 `
b10 Z
b10 T
1'
#1300000
0'
#1310000
b11 T
b11 Z
b11 `
0F
0I
1'
#1320000
0'
#1330000
b100 `
b0 !
b0 4
0.
b100 Z
b0 "
b0 5
0/
b100 T
1'
#1340000
0'
#1350000
b101 T
b101 Z
b101 `
1'
#1360000
0'
#1370000
b110 `
b110 Z
b110 T
1'
#1380000
1%
0'
#1390000
b111 T
b111 Z
b111 `
1G
1'
#1400000
0'
#1410000
1H
b1000 `
b1000 Z
b1000 T
1'
#1420000
0'
#1430000
b1001 T
b1001 Z
b1001 `
1I
1'
#1440000
0'
#1450000
12
1F
0I
b0 `
b0 Z
b0 T
1'
#1460000
0'
#1470000
b100 [
b100 <
b100 V
b1 T
b1 Z
b1111 "
b1111 5
1/
b1 `
b1111 !
b1111 4
1.
02
1'
#1480000
0'
#1490000
b10 `
b10 Z
b10 T
1'
#1500000
0%
0'
#1510000
b11 T
b11 Z
b11 `
0G
1'
#1520000
0'
#1530000
0H
b100 `
b0 !
b0 4
0.
b100 Z
b100 T
1'
#1540000
0'
#1550000
b101 T
b101 Z
b0 "
b0 5
0/
b101 `
1I
1'
#1560000
0'
#1570000
0F
0I
b110 `
b110 Z
b110 T
1'
#1580000
0'
#1590000
b111 T
b111 Z
b111 `
1'
#1600000
0'
#1610000
b1000 `
b1000 Z
b1000 T
1'
#1620000
0'
#1630000
b1001 T
b1001 Z
b1001 `
1'
#1640000
1%
0'
#1650000
1G
b0 `
b0 Z
b0 T
1'
#1660000
0'
#1670000
b1 T
b1 Z
b1111 "
b1111 5
1/
b1 `
b1111 !
b1111 4
1.
1H
1'
#1680000
0'
#1690000
1I
b10 `
b10 Z
b10 T
1'
#1700000
0'
#1710000
b11 T
b11 Z
b11 `
12
1F
0I
1'
#1720000
0'
#1730000
b101 [
02
b100 `
b0 !
b0 4
0.
b100 Z
b100 T
b101 <
b101 V
1'
#1740000
0'
#1750000
b101 T
b101 Z
b101 `
1'
#1760000
0%
0'
#1770000
0G
b110 `
b110 Z
b0 "
b0 5
0/
b110 T
1'
#1780000
0'
#1790000
b111 T
b111 Z
b111 `
0H
1'
#1800000
0'
#1810000
1I
b1000 `
b1000 Z
b1000 T
1'
#1820000
0'
#1830000
b1001 T
b1001 Z
b1001 `
0F
0I
1'
#1840000
0'
#1850000
b0 `
b0 Z
b0 T
1'
#1860000
0'
#1870000
b1 T
b1 Z
b1111 "
b1111 5
1/
b1 `
b1111 !
b1111 4
1.
1'
#1880000
0'
#1890000
b10 `
b10 Z
b10 T
1'
#1900000
1$
0'
#1910000
b11 T
b11 Z
b11 `
1A
1'
#1920000
0'
#1930000
1B
b100 `
b0 !
b0 4
0.
b100 Z
b100 T
1'
#1940000
0'
#1950000
b101 T
b101 Z
b101 `
1C
1'
#1960000
0'
#1970000
13
1@
0C
b110 `
b110 Z
b0 "
b0 5
0/
b110 T
1'
#1980000
0'
#1990000
b1 U
b1 ;
b1 P
b111 T
b111 Z
b111 `
03
1'
#2000000
0'
#2010000
b1000 `
b1000 Z
b1000 T
1'
#2020000
0$
0'
#2030000
b1001 T
b1001 Z
b1001 `
0A
1'
#2040000
0'
#2050000
0B
b0 `
b0 Z
b0 T
1'
#2060000
0'
#2070000
b1 T
b1111 #
b1111 6
10
b1 Z
b1111 "
b1111 5
1/
b1 `
b1111 !
b1111 4
1.
1C
1'
#2080000
0'
#2090000
0@
0C
b10 `
b10 Z
b10 T
b0 #
b0 6
00
1'
#2100000
0'
#2110000
b11 T
b11 Z
b11 `
1'
#2120000
0'
#2130000
b100 `
b0 !
b0 4
0.
b100 Z
b100 T
1'
#2140000
0'
#2150000
b101 T
b101 Z
b101 `
1'
#2160000
1$
0'
#2170000
1A
b110 `
b110 Z
b0 "
b0 5
0/
b110 T
1'
#2180000
0'
#2190000
b111 T
b111 Z
b111 `
1B
1'
#2200000
0'
#2210000
1C
b1000 `
b1000 Z
b1000 T
1'
#2220000
0'
#2230000
b1001 T
b1001 Z
b1001 `
13
1@
0C
1'
#2240000
0'
#2250000
b10 U
03
b0 `
b0 Z
b0 T
b10 ;
b10 P
1'
#2260000
0'
#2270000
b1 T
b1111 #
b1111 6
10
b1 Z
b1111 "
b1111 5
1/
b1 `
b1111 !
b1111 4
1.
1'
#2280000
0$
0'
#2290000
0A
b10 `
b10 Z
b10 T
1'
#2300000
0'
#2310000
b11 T
b0 #
b0 6
00
b11 Z
b11 `
0B
1'
#2320000
0'
#2330000
1C
b100 `
b0 !
b0 4
0.
b100 Z
b100 T
1'
#2340000
0'
#2350000
b101 T
b101 Z
b101 `
0@
0C
1'
#2360000
0'
#2370000
b110 `
b110 Z
b0 "
b0 5
0/
b110 T
1'
#2380000
0'
#2390000
b111 T
b111 Z
b111 `
1'
#2400000
0'
#2410000
b1000 `
b1000 Z
b1000 T
1'
#2420000
1$
0'
#2430000
b1001 T
b1001 Z
b1001 `
1A
1'
#2440000
0'
#2450000
1B
b0 `
b0 Z
b0 T
1'
#2460000
0'
#2470000
b1 T
b1111 #
b1111 6
10
b1 Z
b1111 "
b1111 5
1/
b1 `
b1111 !
b1111 4
1.
1C
1'
#2480000
0'
#2490000
13
1@
0C
b10 `
b10 Z
b10 T
1'
#2500000
0'
#2510000
b11 U
b11 ;
b11 P
b11 T
b0 #
b0 6
00
b11 Z
b11 `
03
1'
#2520000
0'
#2530000
b100 `
b0 !
b0 4
0.
b100 Z
b100 T
1'
#2540000
0$
0'
#2550000
b101 T
b101 Z
b101 `
0A
1'
#2560000
0'
#2570000
0B
b110 `
b110 Z
b0 "
b0 5
0/
b110 T
1'
#2580000
0'
#2590000
b111 T
b111 Z
b111 `
1C
1'
#2600000
0'
#2610000
0@
0C
b1000 `
b1000 Z
b1000 T
1'
#2620000
0'
#2630000
b1001 T
b1001 Z
b1001 `
1'
#2640000
0'
#2650000
b0 `
b0 Z
b0 T
1'
#2660000
0'
#2670000
b1 T
b1111 #
b1111 6
10
b1 Z
b1111 "
b1111 5
1/
b1 `
b1111 !
b1111 4
1.
1'
#2680000
1$
0'
#2690000
1A
b10 `
b10 Z
b10 T
1'
#2700000
0'
#2710000
b11 T
b11 Z
b11 `
1B
1'
#2720000
0'
#2730000
1C
b100 `
b0 !
b0 4
0.
b100 Z
b100 T
b0 #
b0 6
00
1'
#2740000
0'
#2750000
b101 T
b101 Z
b101 `
13
1@
0C
1'
#2760000
0'
#2770000
b100 U
03
b110 `
b110 Z
b0 "
b0 5
0/
b110 T
b100 ;
b100 P
1'
#2780000
0'
#2790000
b111 T
b111 Z
b111 `
1'
#2800000
0$
0'
#2810000
0A
b1000 `
b1000 Z
b1000 T
1'
#2820000
0'
#2830000
b1001 T
b1001 Z
b1001 `
0B
1'
#2840000
0'
#2850000
1C
b0 `
b0 Z
b0 T
1'
#2860000
0'
#2870000
b1 T
b1111 #
b1111 6
10
b1 Z
b1111 "
b1111 5
1/
b1 `
b1111 !
b1111 4
1.
0@
0C
1'
#2880000
0'
#2890000
b10 `
b10 Z
b10 T
1'
#2900000
0'
#2910000
b11 T
b11 Z
b11 `
1'
#2920000
0'
#2930000
b100 `
b0 !
b0 4
0.
b100 Z
b100 T
1'
#2940000
1$
0'
#2950000
b101 T
b0 #
b0 6
00
b101 Z
b101 `
1A
1'
#2960000
0'
#2970000
1B
b110 `
b110 Z
b0 "
b0 5
0/
b110 T
1'
#2980000
0'
#2990000
b111 T
b111 Z
b111 `
1C
1'
#3000000
0'
#3010000
13
1@
0C
b1000 `
b1000 Z
b1000 T
1'
#3020000
0'
#3030000
b101 U
b101 ;
b101 P
b1001 T
b1001 Z
b1001 `
03
1'
#3040000
0'
#3050000
b0 `
b0 Z
b0 T
1'
#3060000
0$
0'
#3070000
b1 T
b1111 #
b1111 6
10
b1 Z
b1111 "
b1111 5
1/
b1 `
b1111 !
b1111 4
1.
0A
1'
#3080000
0'
#3090000
0B
b10 `
b10 Z
b10 T
1'
#3100000
0'
#3110000
b11 T
b11 Z
b11 `
1C
1'
#3120000
0'
#3130000
0@
0C
b100 `
b0 !
b0 4
0.
b100 Z
b100 T
1'
#3140000
0'
#3150000
b101 T
b101 Z
b101 `
1'
#3160000
0'
#3170000
b110 `
b110 Z
b0 "
b0 5
0/
b110 T
b0 #
b0 6
00
1'
#3180000
0'
#3190000
b111 T
b111 Z
b111 `
1'
#3200000
1$
0'
#3210000
1A
b1000 `
b1000 Z
b1000 T
1'
#3220000
0'
#3230000
b1001 T
b1001 Z
b1001 `
1B
1'
#3240000
0'
#3250000
1C
b0 `
b0 Z
b0 T
1'
#3260000
0'
#3270000
b1 T
b1111 #
b1111 6
10
b1 Z
b1111 "
b1111 5
1/
b1 `
b1111 !
b1111 4
1.
13
1@
0C
1'
#3280000
0'
#3290000
b110 U
03
b10 `
b10 Z
b10 T
b110 ;
b110 P
1'
#3300000
0'
#3310000
b11 T
b11 Z
b11 `
1'
#3320000
0$
0'
#3330000
0A
b100 `
b0 !
b0 4
0.
b100 Z
b100 T
1'
#3340000
0'
#3350000
b101 T
b101 Z
b101 `
0B
1'
#3360000
0'
#3370000
1C
b110 `
b110 Z
b0 "
b0 5
0/
b110 T
1'
#3380000
0'
#3390000
b111 T
b0 #
b0 6
00
b111 Z
b111 `
0@
0C
1'
#3400000
0'
#3410000
b1000 `
b1000 Z
b1000 T
1'
#3420000
0'
#3430000
b1001 T
b1001 Z
b1001 `
1'
#3440000
0'
#3450000
b0 `
b0 Z
b0 T
1'
#3460000
1$
0'
#3470000
b1 T
b1111 #
b1111 6
10
b1 Z
b1111 "
b1111 5
1/
b1 `
b1111 !
b1111 4
1.
1A
1'
#3480000
0'
#3490000
1B
b10 `
b10 Z
b10 T
1'
#3500000
0'
#3510000
b11 T
b11 Z
b11 `
1C
1'
#3520000
0'
#3530000
13
1@
0C
b100 `
b0 !
b0 4
0.
b100 Z
b100 T
1'
#3540000
0'
#3550000
b111 U
b111 ;
b111 P
b101 T
b101 Z
b101 `
03
1'
#3560000
0'
#3570000
b110 `
b110 Z
b0 "
b0 5
0/
b110 T
1'
#3580000
0$
0'
#3590000
b111 T
b111 Z
b111 `
0A
1'
#3600000
0'
#3610000
0B
b1000 `
b1000 Z
b1000 T
b0 #
b0 6
00
1'
#3620000
0'
#3630000
b1001 T
b1001 Z
b1001 `
1C
1'
#3640000
0'
#3650000
0@
0C
b0 `
b0 Z
b0 T
1'
#3660000
0'
#3670000
b1 T
b1111 #
b1111 6
10
b1 Z
b1111 "
b1111 5
1/
b1 `
b1111 !
b1111 4
1.
1'
#3680000
0'
#3690000
b10 `
b10 Z
b10 T
1'
#3700000
0'
#3710000
b11 T
b11 Z
b11 `
1'
#3720000
1$
0'
#3730000
1A
b100 `
b0 !
b0 4
0.
b100 Z
b100 T
1'
#3740000
0'
#3750000
b101 T
b101 Z
b101 `
1B
1'
#3760000
0'
#3770000
1C
b110 `
b110 Z
b0 "
b0 5
0/
b110 T
1'
#3780000
0'
#3790000
b111 T
b111 Z
b111 `
13
1@
0C
1'
#3800000
0'
#3810000
b1000 U
03
b1000 `
b1000 Z
b1000 T
b0 #
b0 6
00
b1000 ;
b1000 P
1'
#3820000
0'
#3830000
b1001 T
b1001 Z
b1001 `
1'
#3840000
0$
0'
#3850000
0A
b0 `
b0 Z
b0 T
1'
#3860000
0'
#3870000
b1 T
b1111 #
b1111 6
10
b1 Z
b1111 "
b1111 5
1/
b1 `
b1111 !
b1111 4
1.
0B
1'
#3880000
0'
#3890000
1C
b10 `
b10 Z
b10 T
1'
#3900000
0'
#3910000
b11 T
b11 Z
b11 `
0@
0C
1'
#3920000
0'
#3930000
b100 `
b0 !
b0 4
0.
b100 Z
b100 T
1'
#3940000
0'
#3950000
b101 T
b101 Z
b101 `
1'
#3960000
b1000 b
b101 c
b10 d
0'
#3970000
b110 `
b110 Z
b0 "
b0 5
0/
b110 T
1'
#3980000
0'
#3990000
b111 T
b111 Z
b111 `
1'
#4000000
0'
#4010000
b1000 `
b1000 Z
b1000 T
1'
#4020000
0'
#4030000
b1001 T
b0 #
b0 6
00
b1001 Z
b1001 `
1'
#4040000
0'
#4050000
b0 -
b0 *
b0 +
b0 ,
b0 `
b0 Z
b0 T
1'
#4060000
0'
#4070000
b1 T
b1111 #
b1111 6
10
b1 Z
b1111 "
b1111 5
1/
b1 `
b1111 !
b1111 4
1.
1'
#4071000
b1 -
b1 *
b1 +
b1 ,
#4080000
0'
#4090000
b10 `
b10 Z
b10 T
1'
#4091000
b10 -
b10 *
b10 +
b10 ,
#4100000
0'
#4110000
b11 T
b11 Z
b11 `
1'
#4111000
b11 -
b11 *
b11 +
b11 ,
#4120000
0'
#4130000
b100 `
b0 !
b0 4
0.
b100 Z
b100 T
1'
#4131000
b100 -
b100 *
b100 +
#4140000
0'
#4150000
b101 T
b101 Z
b101 `
1'
#4151000
b101 -
b101 *
b101 +
#4160000
0'
#4170000
b110 `
b110 Z
b0 "
b0 5
0/
b110 T
1'
#4171000
b110 -
b110 *
#4180000
0'
#4190000
b111 T
b111 Z
b111 `
1'
#4191000
b111 -
b111 *
#4200000
0'
#4210000
b1000 `
b1000 Z
b1000 T
1'
#4211000
b1000 -
b1000 *
#4220000
0'
#4230000
b1001 T
b0 #
b0 6
00
b1001 Z
b1001 `
1'
#4231000
b1001 -
#4240000
0'
#4250000
b0 `
b0 Z
b0 T
1'
#4251000
b1010 -
