circuits/02_rgb_pwm/src/pwm_channel.v
`timescale 1ns/1ps
module pwm_channel #(
parameter integer PERIOD_CYCLES = 50_000,
parameter integer LEVELS = 10
) (
input wire clk,
input wire rst_p,
input wire [3:0] level,
output reg pwm
);
localparam integer COUNT_WIDTH = (PERIOD_CYCLES < 2) ? 1 : $clog2(PERIOD_CYCLES);
reg [COUNT_WIDTH-1:0] count;
integer threshold;

always @* begin
if (level >= LEVELS)
threshold = PERIOD_CYCLES;
else
threshold = (PERIOD_CYCLES * level) / LEVELS;
end

always @(posedge clk or posedge rst_p) begin
if (rst_p) begin
count <= {COUNT_WIDTH{1'b0}};
pwm <= 1'b0;
end else begin
pwm <= (count < threshold);
if (count == PERIOD_CYCLES - 1)
count <= {COUNT_WIDTH{1'b0}};
else
count <= count + 1'b1;
end
end
endmodule

circuits/01_led_pwm/src/button_onepulse.v
`timescale 1ns/1ps
module button_onepulse #(
parameter integer STABLE_CYCLES = 1_000_000
) (
input wire clk,
input wire rst_p,
input wire button,
output reg pulse
);
(* ASYNC_REG = "TRUE" *) reg button_meta;
(* ASYNC_REG = "TRUE" *) reg button_sync;
localparam integer COUNT_WIDTH = (STABLE_CYCLES < 2) ? 1 : $clog2(STABLE_CYCLES);
reg [COUNT_WIDTH-1:0] stable_count;
reg accepted;

always @(posedge clk or posedge rst_p) begin
if (rst_p) begin
button_meta <= 1'b0;
button_sync <= 1'b0;
end else begin
button_meta <= button;
button_sync <= button_meta;
end
end

always @(posedge clk or posedge rst_p) begin
if (rst_p) begin
stable_count <= {COUNT_WIDTH{1'b0}};
accepted <= 1'b0;
pulse <= 1'b0;
end else begin
pulse <= 1'b0;
if (button_sync == accepted) begin
stable_count <= {COUNT_WIDTH{1'b0}};
end else if (stable_count == STABLE_CYCLES - 1) begin
stable_count <= {COUNT_WIDTH{1'b0}};
accepted <= button_sync;
pulse <= button_sync;
end else begin
stable_count <= stable_count + 1'b1;
end
end
end
endmodule

circuits/01_led_pwm/src/lab3_led_pwm.v
`timescale 1ns/1ps
module lab3_led_pwm #(
parameter integer CLK_HZ = 50_000_000,
parameter integer PWM_HZ = 1_000,
parameter integer LEVELS = 10,
parameter integer DEBOUNCE_CYCLES = 1_000_000
) (
input wire clk_50mhz,
input wire rst_p,
input wire button,
output wire [7:0] led
);
wire press;
wire pwm;
reg [3:0] level;

button_onepulse #(.STABLE_CYCLES(DEBOUNCE_CYCLES)) u_button (
.clk(clk_50mhz), .rst_p(rst_p), .button(button), .pulse(press)
);

always @(posedge clk_50mhz or posedge rst_p) begin
if (rst_p)
level <= 4'd0;
else if (press)
level <= (level == LEVELS) ? 4'd0 : level + 1'b1;
end

pwm_channel #(.PERIOD_CYCLES(CLK_HZ / PWM_HZ), .LEVELS(LEVELS)) u_pwm (
.clk(clk_50mhz), .rst_p(rst_p), .level(level), .pwm(pwm)
);

assign led = {8{pwm}};
endmodule

evidence/01_led_pwm/levels5_modified/tb_led_pwm.sv
`timescale 1ns/1ps
module tb_led_pwm;
reg clk_50mhz=0, rst_p=1, button=0;
wire [7:0] led;
integer checks=0, high_count, i;
always #10 clk_50mhz=~clk_50mhz;
lab3_led_pwm #(.CLK_HZ(1000),.PWM_HZ(100),.LEVELS(5),.DEBOUNCE_CYCLES(2)) dut
(.clk_50mhz(clk_50mhz),.rst_p(rst_p),.button(button),.led(led));

task press_button;
begin
@(negedge clk_50mhz); button=1; repeat(6) @(negedge clk_50mhz);
button=0; repeat(6) @(negedge clk_50mhz);
end endtask

task expect_level(input integer expected);
begin
wait(dut.u_pwm.count==0); high_count=0;
for(i=0;i<10;i=i+1) begin @(posedge clk_50mhz); #1; if(led[0]) high_count=high_count+1; end
if(high_count!==expected) $fatal(1,"level=%0d high=%0d",expected,high_count);
$display("CHECK expected_high=%0d observed_high=%0d time=%0t", expected, high_count, $time);
checks=checks+1;
end endtask

initial begin
$dumpfile("wave.vcd"); $dumpvars(0,tb_led_pwm);
repeat(3) @(negedge clk_50mhz); rst_p=0;
expect_level(0);
repeat(3) press_button(); expect_level(3);
repeat(7) press_button(); expect_level(10);
press_button(); expect_level(0);
$display("LAB3_LED_PWM_PASS checks=%0d",checks); $finish;
end
initial begin #20000; $fatal(1,"timeout"); end
endmodule

evidence/01_led_pwm/levels5_modified/wave.vcd
$date
	Sun Sep 27 23:13:59 2026
$end
$version
	Icarus Verilog
$end
$timescale
	1ps
$end
$scope module tb_led_pwm $end
$var wire 8 ! led [7:0] $end
$var reg 1 " button $end
$var reg 1 # clk_50mhz $end
$var reg 1 $ rst_p $end
$var integer 32 % checks [31:0] $end
$var integer 32 & high_count [31:0] $end
$var integer 32 ' i [31:0] $end
$scope module dut $end
$var wire 1 " button $end
$var wire 1 # clk_50mhz $end
$var wire 1 $ rst_p $end
$var wire 1 ( pwm $end
$var wire 1 ) press $end
$var wire 8 * led [7:0] $end
$var parameter 32 + CLK_HZ $end
$var parameter 32 , DEBOUNCE_CYCLES $end
$var parameter 32 - LEVELS $end
$var parameter 32 . PWM_HZ $end
$var reg 4 / level [3:0] $end
$scope module u_button $end
$var wire 1 " button $end
$var wire 1 # clk $end
$var wire 1 $ rst_p $end
$var parameter 32 0 COUNT_WIDTH $end
$var parameter 32 1 STABLE_CYCLES $end
$var reg 1 2 accepted $end
$var reg 1 3 button_meta $end
$var reg 1 4 button_sync $end
$var reg 1 ) pulse $end
$var reg 1 5 stable_count $end
$upscope $end
$scope module u_pwm $end
$var wire 1 # clk $end
$var wire 4 6 level [3:0] $end
$var wire 1 $ rst_p $end
$var parameter 32 7 COUNT_WIDTH $end
$var parameter 32 8 LEVELS $end
$var parameter 32 9 PERIOD_CYCLES $end
$var reg 4 : count [3:0] $end
$var reg 1 ( pwm $end
$var integer 32 ; threshold [31:0] $end
$upscope $end
$upscope $end
$scope task expect_level $end
$var integer 32 < expected [31:0] $end
$upscope $end
$scope task press_button $end
$upscope $end
$upscope $end
$enddefinitions $end
$comment Show the parameter values. $end
$dumpall
b1010 9
b101 8
b100 7
b10 1
b1 0
b1100100 .
b101 -
b10 ,
b1111101000 +
$end
#0
$dumpvars
bx <
bx ;
bx :
bx 6
x5
x4
x3
x2
bx /
bx *
x)
x(
bx '
bx &
b0 %
1$
0#
0"
bx !
$end
#10000
b0 ;
04
03
0)
02
05
b0 !
b0 *
0(
b0 :
b0 /
b0 6
1#
#20000
0#
#30000
1#
#40000
0#
#50000
1#
#60000
b0 '
b0 &
b0 <
0$
0#
#70000
b1 :
1#
#71000
b1 '
#80000
0#
#90000
b10 :
1#
#91000
b10 '
#100000
0#
#110000
b11 :
1#
#111000
b11 '
#120000
0#
#130000
b100 :
1#
#131000
b100 '
#140000
0#
#150000
b101 :
1#
#151000
b101 '
#160000
0#
#170000
b110 :
1#
#171000
b110 '
#180000
0#
#190000
b111 :
1#
#191000
b111 '
#200000
0#
#210000
b1000 :
1#
#211000
b1000 '
#220000
0#
#230000
b1001 :
1#
#231000
b1001 '
#240000
0#
#250000
b0 :
1#
#251000
b1 %
b1010 '
#260000
1"
0#
#270000
b1 :
13
1#
#280000
0#
#290000
14
b10 :
1#
#300000
0#
#310000
b11 :
15
1#
#320000
0#
#330000
1)
12
05
b100 :
1#
#340000
0#
#350000
b10 ;
b1 /
b1 6
b101 :
0)
1#
#360000
0#
#370000
b110 :
1#
#380000
0"
0#
#390000
b111 :
03
1#
#400000
0#
#410000
04
b1000 :
1#
#420000
0#
#430000
b1001 :
15
1#
#440000
0#
#450000
02
05
b0 :
1#
#460000
0#
#470000
b1 :
b11111111 !
b11111111 *
1(
1#
#480000
0#
#490000
b10 :
1#
#500000
0#
#510000
b11 :
b0 !
b0 *
0(
1#
#520000
1"
0#
#530000
13
b100 :
1#
#540000
0#
#550000
b101 :
14
1#
#560000
0#
#570000
15
b110 :
1#
#580000
0#
#590000
b111 :
1)
12
05
1#
#600000
0#
#610000
b100 ;
0)
b1000 :
b10 /
b10 6
1#
#620000
0#
#630000
b1001 :
1#
#640000
0"
0#
#650000
03
b0 :
1#
#660000
0#
#670000
b1 :
b11111111 !
b11111111 *
1(
04
1#
#680000
0#
#690000
15
b10 :
1#
#700000
0#
#710000
b11 :
02
05
1#
#720000
0#
#730000
b100 :
1#
#740000
0#
#750000
b101 :
b0 !
b0 *
0(
1#
#760000
0#
#770000
b110 :
1#
#780000
1"
0#
#790000
b111 :
13
1#
#800000
0#
#810000
14
b1000 :
1#
#820000
0#
#830000
b1001 :
15
1#
#840000
0#
#850000
1)
12
05
b0 :
1#
#860000
0#
#870000
b110 ;
b11 /
b11 6
b1 :
b11111111 !
b11111111 *
1(
0)
1#
#880000
0#
#890000
b10 :
1#
#900000
0"
0#
#910000
b11 :
03
1#
#920000
0#
#930000
04
b100 :
1#
#940000
0#
#950000
b101 :
15
1#
#960000
0#
#970000
02
05
b110 :
1#
#980000
0#
#990000
b111 :
b0 !
b0 *
0(
1#
#1000000
0#
#1010000
b1000 :
1#
#1020000
b11 <
0#
#1030000
b1001 :
1#
#1040000
0#
#1050000
b0 '
b0 :
1#
#1060000
0#
#1070000
b1 :
b11111111 !
b11111111 *
1(
1#
#1071000
b1 '
b1 &
#1080000
0#
#1090000
b10 :
1#
#1091000
b10 '
b10 &
#1100000
0#
#1110000
b11 :
1#
#1111000
b11 '
b11 &
#1120000
0#
#1130000
b100 :
1#
#1131000
b100 '
b100 &
#1140000
0#
#1150000
b101 :
1#
#1151000
b101 '
b101 &
#1160000
0#
#1170000
b110 :
1#
#1171000
b110 '
b110 &
#1180000
0#
#1190000
b111 :
b0 !
b0 *
0(
1#
#1191000
b111 '
#1200000
0#
#1210000
b1000 :
1#
#1211000
b1000 '
#1220000
0#
#1230000
b1001 :
1#
#1231000
b1001 '
#1240000
0#
#1250000
b0 :
1#
#1251000
b1010 '
